flagbox/__init__.py
flagbox/mysql.py
FlagBox-0.21.dist-info/LICENSE
FlagBox-0.21.dist-info/METADATA
FlagBox-0.21.dist-info/WHEEL
FlagBox-0.21.dist-info/top_level.txt
FlagBox-0.21.dist-info/RECORD
