Metadata-Version: 2.1
Name: FlagBox
Version: 0.21
Summary: A simple mysql orm for python3
Home-page: https://github.com/lwaix/flagbox
Author: lwaix
Author-email: 1494645263@qq.com
License: MIT
Platform: UNKNOWN
Requires-Dist: PyMySQL
